realtimex_frappe/__init__.py
realtimex_frappe/__main__.py
realtimex_frappe/cli.py
realtimex_frappe/commands/__init__.py
realtimex_frappe/commands/new_site.py
realtimex_frappe/commands/run.py
realtimex_frappe/commands/setup.py
realtimex_frappe/config/__init__.py
realtimex_frappe/config/env.py
realtimex_frappe/config/loader.py
realtimex_frappe/config/schema.py
realtimex_frappe/data/__init__.py
realtimex_frappe/data/default.json
realtimex_frappe/utils/__init__.py
realtimex_frappe/utils/bench.py
realtimex_frappe/utils/environment.py
realtimex_frappe/utils/paths.py
realtimex_frappe-0.5.0.dist-info/METADATA
realtimex_frappe-0.5.0.dist-info/WHEEL
realtimex_frappe-0.5.0.dist-info/entry_points.txt
realtimex_frappe-0.5.0.dist-info/RECORD
