Metadata-Version: 2.4
Name: realtimex-frappe
Version: 0.5.0
Summary: CLI tool for streamlined Frappe/ERPNext site setup with PostgreSQL and bundled binaries support
Author: Realtimex
License: MIT
Keywords: bench,cli,erpnext,frappe,setup
Classifier: Development Status :: 3 - Alpha
Classifier: Environment :: Console
Classifier: Intended Audience :: Developers
Classifier: License :: OSI Approved :: MIT License
Classifier: Operating System :: MacOS
Classifier: Operating System :: POSIX :: Linux
Classifier: Programming Language :: Python :: 3
Classifier: Programming Language :: Python :: 3.11
Classifier: Programming Language :: Python :: 3.12
Classifier: Topic :: Software Development :: Build Tools
Requires-Python: >=3.11
Requires-Dist: click>=8.1.0
Requires-Dist: frappe-bench>=5.28.0
Requires-Dist: pydantic>=2.0.0
Requires-Dist: rich>=13.0.0
Provides-Extra: dev
Requires-Dist: pytest-cov>=4.0.0; extra == 'dev'
Requires-Dist: pytest>=7.0.0; extra == 'dev'
